{
  "project_info": {
    "project_number": "807292297844",
    "project_id": "t4-sers",
    "storage_bucket": "t4-sers.appspot.com"
  },
  "client": [
    {
      "client_info": {
        "mobilesdk_app_id": "1:807292297844:android:f9a34489931eaba50ee721",
        "android_client_info": {
          "package_name": "t4.sres"
        }
      },
      "oauth_client": [
        {
          "client_id": "807292297844-70v8ot7f4f36du1tih4019h0jd580pfd.apps.googleusercontent.com",
          "client_type": 1,
          "android_info": {
            "package_name": "t4.sres",
            "certificate_hash": "7c765dd698d96588456f818fff67bf2704cd1cad"
          }
        },
        {
          "client_id": "807292297844-6bnk0tk5jmu72gpqij34kv1ionqro1k1.apps.googleusercontent.com",
          "client_type": 3
        }
      ],
      "api_key": [
        {
          "current_key": "AIzaSyB6TmaPCTMa8ncXkgBIbzKd9lN1k6rteiM"
        }
      ],
      "services": {
        "appinvite_service": {
          "other_platform_oauth_client": [
            {
              "client_id": "807292297844-6bnk0tk5jmu72gpqij34kv1ionqro1k1.apps.googleusercontent.com",
              "client_type": 3
            }
          ]
        }
      }
    }
  ],
  "configuration_version": "1"
}